shabti
