Metadata-Version: 1.0
Name: Shabti
Version: 0.4.3
Summary: Pylons template with Elixir ORM bindings
Home-page: http://www.bitbucket.org/gjhiggins/shabti
Author: Graham Higgins
Author-email: gjh@bel-epa.com
License: MIT License
Keywords: web wsgi framework sqlalchemy elixir pylons paste template
Platform: UNKNOWN
Classifier: Development Status :: 5 - Production/Stable
Classifier: Framework :: Pylons
Classifier: Intended Audience :: Developers
Classifier: License :: OSI Approved :: MIT License
Classifier: Programming Language :: Python
Classifier: Topic :: Internet :: WWW/HTTP
Classifier: Topic :: Internet :: WWW/HTTP :: Dynamic Content
Classifier: Topic :: Internet :: WWW/HTTP :: WSGI
Classifier: Topic :: Software Development :: Libraries :: Python Modules
